<?xml version="1.0"?>
<ownershipDocument>

    <schemaVersion>X0306</schemaVersion>

    <documentType>4</documentType>

    <periodOfReport>2022-02-26</periodOfReport>

    <issuer>
        <issuerCik>0000078003</issuerCik>
        <issuerName>PFIZER INC</issuerName>
        <issuerTradingSymbol>PFE</issuerTradingSymbol>
    </issuer>

    <reportingOwner>
        <reportingOwnerId>
            <rptOwnerCik>0001263544</rptOwnerCik>
            <rptOwnerName>SUSMAN SALLY</rptOwnerName>
        </reportingOwnerId>
        <reportingOwnerAddress>
            <rptOwnerStreet1>PFIZER INC.-CORP. SECRETARY</rptOwnerStreet1>
            <rptOwnerStreet2>235 EAST 42ND ST.</rptOwnerStreet2>
            <rptOwnerCity>NEW YORK</rptOwnerCity>
            <rptOwnerState>NY</rptOwnerState>
            <rptOwnerZipCode>10017</rptOwnerZipCode>
            <rptOwnerStateDescription></rptOwnerStateDescription>
        </reportingOwnerAddress>
        <reportingOwnerRelationship>
            <isOfficer>1</isOfficer>
            <officerTitle>Executive Vice President</officerTitle>
        </reportingOwnerRelationship>
    </reportingOwner>

    <nonDerivativeTable>
        <nonDerivativeTransaction>
            <securityTitle>
                <value>Common Stock</value>
            </securityTitle>
            <transactionDate>
                <value>2022-02-26</value>
            </transactionDate>
            <transactionCoding>
                <transactionFormType>4</transactionFormType>
                <transactionCode>M</transactionCode>
                <equitySwapInvolved>0</equitySwapInvolved>
            </transactionCoding>
            <transactionAmounts>
                <transactionShares>
                    <value>63580.0000</value>
                    <footnoteId id="F1"/>
                </transactionShares>
                <transactionPricePerShare>
                    <value>25.6000</value>
                </transactionPricePerShare>
                <transactionAcquiredDisposedCode>
                    <value>A</value>
                </transactionAcquiredDisposedCode>
            </transactionAmounts>
            <postTransactionAmounts>
                <sharesOwnedFollowingTransaction>
                    <value>172880.0000</value>
                </sharesOwnedFollowingTransaction>
            </postTransactionAmounts>
            <ownershipNature>
                <directOrIndirectOwnership>
                    <value>D</value>
                </directOrIndirectOwnership>
            </ownershipNature>
        </nonDerivativeTransaction>
        <nonDerivativeTransaction>
            <securityTitle>
                <value>Common Stock</value>
            </securityTitle>
            <transactionDate>
                <value>2022-02-26</value>
            </transactionDate>
            <transactionCoding>
                <transactionFormType>4</transactionFormType>
                <transactionCode>F</transactionCode>
                <equitySwapInvolved>0</equitySwapInvolved>
            </transactionCoding>
            <transactionAmounts>
                <transactionShares>
                    <value>18745.0000</value>
                    <footnoteId id="F2"/>
                </transactionShares>
                <transactionPricePerShare>
                    <value>47.7200</value>
                    <footnoteId id="F3"/>
                </transactionPricePerShare>
                <transactionAcquiredDisposedCode>
                    <value>D</value>
                </transactionAcquiredDisposedCode>
            </transactionAmounts>
            <postTransactionAmounts>
                <sharesOwnedFollowingTransaction>
                    <value>154135.0000</value>
                </sharesOwnedFollowingTransaction>
            </postTransactionAmounts>
            <ownershipNature>
                <directOrIndirectOwnership>
                    <value>D</value>
                </directOrIndirectOwnership>
            </ownershipNature>
        </nonDerivativeTransaction>
        <nonDerivativeTransaction>
            <securityTitle>
                <value>Common Stock</value>
            </securityTitle>
            <transactionDate>
                <value>2022-02-26</value>
            </transactionDate>
            <transactionCoding>
                <transactionFormType>4</transactionFormType>
                <transactionCode>F</transactionCode>
                <equitySwapInvolved>0</equitySwapInvolved>
            </transactionCoding>
            <transactionAmounts>
                <transactionShares>
                    <value>29685.0000</value>
                    <footnoteId id="F4"/>
                </transactionShares>
                <transactionPricePerShare>
                    <value>50.6400</value>
                    <footnoteId id="F5"/>
                </transactionPricePerShare>
                <transactionAcquiredDisposedCode>
                    <value>D</value>
                </transactionAcquiredDisposedCode>
            </transactionAmounts>
            <postTransactionAmounts>
                <sharesOwnedFollowingTransaction>
                    <value>124450.0000</value>
                </sharesOwnedFollowingTransaction>
            </postTransactionAmounts>
            <ownershipNature>
                <directOrIndirectOwnership>
                    <value>D</value>
                </directOrIndirectOwnership>
            </ownershipNature>
        </nonDerivativeTransaction>
        <nonDerivativeHolding>
            <securityTitle>
                <value>Common Stock</value>
            </securityTitle>
            <postTransactionAmounts>
                <sharesOwnedFollowingTransaction>
                    <value>747.0000</value>
                </sharesOwnedFollowingTransaction>
            </postTransactionAmounts>
            <ownershipNature>
                <directOrIndirectOwnership>
                    <value>I</value>
                </directOrIndirectOwnership>
                <natureOfOwnership>
                    <value>By Rule 16b-3 Plan</value>
                </natureOfOwnership>
            </ownershipNature>
        </nonDerivativeHolding>
    </nonDerivativeTable>

    <derivativeTable>
        <derivativeTransaction>
            <securityTitle>
                <value>Stock Appreciation Rights</value>
            </securityTitle>
            <conversionOrExercisePrice>
                <value>25.6000</value>
            </conversionOrExercisePrice>
            <transactionDate>
                <value>2022-02-26</value>
            </transactionDate>
            <transactionCoding>
                <transactionFormType>4</transactionFormType>
                <transactionCode>M</transactionCode>
                <equitySwapInvolved>0</equitySwapInvolved>
            </transactionCoding>
            <transactionAmounts>
                <transactionShares>
                    <value>63580.0000</value>
                </transactionShares>
                <transactionPricePerShare>
                    <value>0.0000</value>
                </transactionPricePerShare>
                <transactionAcquiredDisposedCode>
                    <value>D</value>
                </transactionAcquiredDisposedCode>
            </transactionAmounts>
            <exerciseDate>
                <value>2022-02-26</value>
            </exerciseDate>
            <expirationDate>
                <value>2022-02-26</value>
            </expirationDate>
            <underlyingSecurity>
                <underlyingSecurityTitle>
                    <value>Common Stock</value>
                </underlyingSecurityTitle>
                <underlyingSecurityShares>
                    <value>63580.0000</value>
                </underlyingSecurityShares>
            </underlyingSecurity>
            <postTransactionAmounts>
                <sharesOwnedFollowingTransaction>
                    <value>0.0000</value>
                </sharesOwnedFollowingTransaction>
            </postTransactionAmounts>
            <ownershipNature>
                <directOrIndirectOwnership>
                    <value>D</value>
                </directOrIndirectOwnership>
            </ownershipNature>
        </derivativeTransaction>
        <derivativeTransaction>
            <securityTitle>
                <value>Phantom Stock Units</value>
            </securityTitle>
            <conversionOrExercisePrice>
                <footnoteId id="F6"/>
            </conversionOrExercisePrice>
            <transactionDate>
                <value>2022-02-28</value>
            </transactionDate>
            <transactionCoding>
                <transactionFormType>4</transactionFormType>
                <transactionCode>A</transactionCode>
                <equitySwapInvolved>0</equitySwapInvolved>
            </transactionCoding>
            <transactionAmounts>
                <transactionShares>
                    <value>58623.0000</value>
                    <footnoteId id="F7"/>
                </transactionShares>
                <transactionPricePerShare>
                    <value>0.0000</value>
                </transactionPricePerShare>
                <transactionAcquiredDisposedCode>
                    <value>A</value>
                </transactionAcquiredDisposedCode>
            </transactionAmounts>
            <exerciseDate>
                <footnoteId id="F8"/>
            </exerciseDate>
            <expirationDate>
                <footnoteId id="F8"/>
            </expirationDate>
            <underlyingSecurity>
                <underlyingSecurityTitle>
                    <value>Common Stock</value>
                </underlyingSecurityTitle>
                <underlyingSecurityShares>
                    <value>58623.0000</value>
                </underlyingSecurityShares>
            </underlyingSecurity>
            <postTransactionAmounts>
                <sharesOwnedFollowingTransaction>
                    <value>80225.0000</value>
                </sharesOwnedFollowingTransaction>
            </postTransactionAmounts>
            <ownershipNature>
                <directOrIndirectOwnership>
                    <value>D</value>
                </directOrIndirectOwnership>
            </ownershipNature>
        </derivativeTransaction>
    </derivativeTable>

    <footnotes>
        <footnote id="F1">The reported transaction constitutes the earn-out of stock appreciation rights (including dividend equivalents thereon).</footnote>
        <footnote id="F2">The reported transaction constitutes the withholding of shares to satisfy tax obligations in connection with earn-out of stock appreciation rights.</footnote>
        <footnote id="F3">Price is the closing price of Pfizer common stock on February 25, 2022.</footnote>
        <footnote id="F4">The reported transaction constitutes the withholding of shares to cover payment of exercise price in connection with earn-out of stock appreciation rights (including dividend equivalents thereon).</footnote>
        <footnote id="F5">Under the terms of the settlement of the stock appreciation rights the 20-day average of the closing prices of Pfizer common stock ending on the settlement date is used.</footnote>
        <footnote id="F6">Each unit represents one phantom share of common stock.</footnote>
        <footnote id="F7">The reported transaction constitutes the earn-out of Performance Share Awards (including dividend equivalents thereon) which have been deferred into the Pfizer Inc. Deferred Compensation Plan.</footnote>
        <footnote id="F8">The units, held under the Deferred Compensation Plan, are paid in cash following the reporting person's separation from service and may be transferred by the reporting person into an alternative investment account at any time.</footnote>
    </footnotes>

    <ownerSignature>
        <signatureName>Susan E. Grant, by power of atty., for Sally Susman</signatureName>
        <signatureDate>2022-03-01</signatureDate>
    </ownerSignature>
</ownershipDocument>