<?xml version="1.0"?>
<ownershipDocument>

    <schemaVersion>X0306</schemaVersion>

    <documentType>4</documentType>

    <periodOfReport>2016-05-09</periodOfReport>

    <issuer>
        <issuerCik>0000078003</issuerCik>
        <issuerName>PFIZER INC</issuerName>
        <issuerTradingSymbol>PFE</issuerTradingSymbol>
    </issuer>

    <reportingOwner>
        <reportingOwnerId>
            <rptOwnerCik>0001263544</rptOwnerCik>
            <rptOwnerName>SUSMAN SALLY</rptOwnerName>
        </reportingOwnerId>
        <reportingOwnerAddress>
            <rptOwnerStreet1>PFIZER INC.-CORP. SECRETARY</rptOwnerStreet1>
            <rptOwnerStreet2>235 EAST 42ND ST.</rptOwnerStreet2>
            <rptOwnerCity>NEW YORK</rptOwnerCity>
            <rptOwnerState>NY</rptOwnerState>
            <rptOwnerZipCode>10017</rptOwnerZipCode>
            <rptOwnerStateDescription></rptOwnerStateDescription>
        </reportingOwnerAddress>
        <reportingOwnerRelationship>
            <isOfficer>1</isOfficer>
            <officerTitle>Executive Vice President</officerTitle>
        </reportingOwnerRelationship>
    </reportingOwner>

    <nonDerivativeTable>
        <nonDerivativeTransaction>
            <securityTitle>
                <value>Common Stock</value>
            </securityTitle>
            <transactionDate>
                <value>2016-05-09</value>
            </transactionDate>
            <transactionCoding>
                <transactionFormType>4</transactionFormType>
                <transactionCode>M</transactionCode>
                <equitySwapInvolved>0</equitySwapInvolved>
            </transactionCoding>
            <transactionAmounts>
                <transactionShares>
                    <value>23884.0000</value>
                </transactionShares>
                <transactionPricePerShare>
                    <value>22.2800</value>
                </transactionPricePerShare>
                <transactionAcquiredDisposedCode>
                    <value>A</value>
                </transactionAcquiredDisposedCode>
            </transactionAmounts>
            <postTransactionAmounts>
                <sharesOwnedFollowingTransaction>
                    <value>199735.0000</value>
                </sharesOwnedFollowingTransaction>
            </postTransactionAmounts>
            <ownershipNature>
                <directOrIndirectOwnership>
                    <value>D</value>
                </directOrIndirectOwnership>
            </ownershipNature>
        </nonDerivativeTransaction>
        <nonDerivativeTransaction>
            <securityTitle>
                <value>Common Stock</value>
            </securityTitle>
            <transactionDate>
                <value>2016-05-09</value>
            </transactionDate>
            <transactionCoding>
                <transactionFormType>4</transactionFormType>
                <transactionCode>S</transactionCode>
                <equitySwapInvolved>0</equitySwapInvolved>
            </transactionCoding>
            <transactionAmounts>
                <transactionShares>
                    <value>100.0000</value>
                </transactionShares>
                <transactionPricePerShare>
                    <value>33.8000</value>
                </transactionPricePerShare>
                <transactionAcquiredDisposedCode>
                    <value>D</value>
                </transactionAcquiredDisposedCode>
            </transactionAmounts>
            <postTransactionAmounts>
                <sharesOwnedFollowingTransaction>
                    <value>199635.0000</value>
                </sharesOwnedFollowingTransaction>
            </postTransactionAmounts>
            <ownershipNature>
                <directOrIndirectOwnership>
                    <value>D</value>
                </directOrIndirectOwnership>
            </ownershipNature>
        </nonDerivativeTransaction>
        <nonDerivativeTransaction>
            <securityTitle>
                <value>Common Stock</value>
            </securityTitle>
            <transactionDate>
                <value>2016-05-09</value>
            </transactionDate>
            <transactionCoding>
                <transactionFormType>4</transactionFormType>
                <transactionCode>S</transactionCode>
                <equitySwapInvolved>0</equitySwapInvolved>
            </transactionCoding>
            <transactionAmounts>
                <transactionShares>
                    <value>200.0000</value>
                </transactionShares>
                <transactionPricePerShare>
                    <value>33.8400</value>
                </transactionPricePerShare>
                <transactionAcquiredDisposedCode>
                    <value>D</value>
                </transactionAcquiredDisposedCode>
            </transactionAmounts>
            <postTransactionAmounts>
                <sharesOwnedFollowingTransaction>
                    <value>199435.0000</value>
                </sharesOwnedFollowingTransaction>
            </postTransactionAmounts>
            <ownershipNature>
                <directOrIndirectOwnership>
                    <value>D</value>
                </directOrIndirectOwnership>
            </ownershipNature>
        </nonDerivativeTransaction>
        <nonDerivativeTransaction>
            <securityTitle>
                <value>Common Stock</value>
            </securityTitle>
            <transactionDate>
                <value>2016-05-09</value>
            </transactionDate>
            <transactionCoding>
                <transactionFormType>4</transactionFormType>
                <transactionCode>S</transactionCode>
                <equitySwapInvolved>0</equitySwapInvolved>
            </transactionCoding>
            <transactionAmounts>
                <transactionShares>
                    <value>300.0000</value>
                </transactionShares>
                <transactionPricePerShare>
                    <value>33.8100</value>
                </transactionPricePerShare>
                <transactionAcquiredDisposedCode>
                    <value>D</value>
                </transactionAcquiredDisposedCode>
            </transactionAmounts>
            <postTransactionAmounts>
                <sharesOwnedFollowingTransaction>
                    <value>199135.0000</value>
                </sharesOwnedFollowingTransaction>
            </postTransactionAmounts>
            <ownershipNature>
                <directOrIndirectOwnership>
                    <value>D</value>
                </directOrIndirectOwnership>
            </ownershipNature>
        </nonDerivativeTransaction>
        <nonDerivativeTransaction>
            <securityTitle>
                <value>Common Stock</value>
            </securityTitle>
            <transactionDate>
                <value>2016-05-09</value>
            </transactionDate>
            <transactionCoding>
                <transactionFormType>4</transactionFormType>
                <transactionCode>S</transactionCode>
                <equitySwapInvolved>0</equitySwapInvolved>
            </transactionCoding>
            <transactionAmounts>
                <transactionShares>
                    <value>400.0000</value>
                </transactionShares>
                <transactionPricePerShare>
                    <value>33.8500</value>
                </transactionPricePerShare>
                <transactionAcquiredDisposedCode>
                    <value>D</value>
                </transactionAcquiredDisposedCode>
            </transactionAmounts>
            <postTransactionAmounts>
                <sharesOwnedFollowingTransaction>
                    <value>198735.0000</value>
                </sharesOwnedFollowingTransaction>
            </postTransactionAmounts>
            <ownershipNature>
                <directOrIndirectOwnership>
                    <value>D</value>
                </directOrIndirectOwnership>
            </ownershipNature>
        </nonDerivativeTransaction>
        <nonDerivativeTransaction>
            <securityTitle>
                <value>Common Stock</value>
            </securityTitle>
            <transactionDate>
                <value>2016-05-09</value>
            </transactionDate>
            <transactionCoding>
                <transactionFormType>4</transactionFormType>
                <transactionCode>S</transactionCode>
                <equitySwapInvolved>0</equitySwapInvolved>
            </transactionCoding>
            <transactionAmounts>
                <transactionShares>
                    <value>400.0000</value>
                </transactionShares>
                <transactionPricePerShare>
                    <value>33.7400</value>
                </transactionPricePerShare>
                <transactionAcquiredDisposedCode>
                    <value>D</value>
                </transactionAcquiredDisposedCode>
            </transactionAmounts>
            <postTransactionAmounts>
                <sharesOwnedFollowingTransaction>
                    <value>198335.0000</value>
                </sharesOwnedFollowingTransaction>
            </postTransactionAmounts>
            <ownershipNature>
                <directOrIndirectOwnership>
                    <value>D</value>
                </directOrIndirectOwnership>
            </ownershipNature>
        </nonDerivativeTransaction>
        <nonDerivativeTransaction>
            <securityTitle>
                <value>Common Stock</value>
            </securityTitle>
            <transactionDate>
                <value>2016-05-09</value>
            </transactionDate>
            <transactionCoding>
                <transactionFormType>4</transactionFormType>
                <transactionCode>S</transactionCode>
                <equitySwapInvolved>0</equitySwapInvolved>
            </transactionCoding>
            <transactionAmounts>
                <transactionShares>
                    <value>500.0000</value>
                </transactionShares>
                <transactionPricePerShare>
                    <value>33.8820</value>
                </transactionPricePerShare>
                <transactionAcquiredDisposedCode>
                    <value>D</value>
                </transactionAcquiredDisposedCode>
            </transactionAmounts>
            <postTransactionAmounts>
                <sharesOwnedFollowingTransaction>
                    <value>197835.0000</value>
                </sharesOwnedFollowingTransaction>
            </postTransactionAmounts>
            <ownershipNature>
                <directOrIndirectOwnership>
                    <value>D</value>
                </directOrIndirectOwnership>
            </ownershipNature>
        </nonDerivativeTransaction>
        <nonDerivativeTransaction>
            <securityTitle>
                <value>Common Stock</value>
            </securityTitle>
            <transactionDate>
                <value>2016-05-09</value>
            </transactionDate>
            <transactionCoding>
                <transactionFormType>4</transactionFormType>
                <transactionCode>S</transactionCode>
                <equitySwapInvolved>0</equitySwapInvolved>
            </transactionCoding>
            <transactionAmounts>
                <transactionShares>
                    <value>700.0000</value>
                </transactionShares>
                <transactionPricePerShare>
                    <value>33.7800</value>
                </transactionPricePerShare>
                <transactionAcquiredDisposedCode>
                    <value>D</value>
                </transactionAcquiredDisposedCode>
            </transactionAmounts>
            <postTransactionAmounts>
                <sharesOwnedFollowingTransaction>
                    <value>197135.0000</value>
                </sharesOwnedFollowingTransaction>
            </postTransactionAmounts>
            <ownershipNature>
                <directOrIndirectOwnership>
                    <value>D</value>
                </directOrIndirectOwnership>
            </ownershipNature>
        </nonDerivativeTransaction>
        <nonDerivativeTransaction>
            <securityTitle>
                <value>Common Stock</value>
            </securityTitle>
            <transactionDate>
                <value>2016-05-09</value>
            </transactionDate>
            <transactionCoding>
                <transactionFormType>4</transactionFormType>
                <transactionCode>S</transactionCode>
                <equitySwapInvolved>0</equitySwapInvolved>
            </transactionCoding>
            <transactionAmounts>
                <transactionShares>
                    <value>1100.0000</value>
                </transactionShares>
                <transactionPricePerShare>
                    <value>33.8300</value>
                </transactionPricePerShare>
                <transactionAcquiredDisposedCode>
                    <value>D</value>
                </transactionAcquiredDisposedCode>
            </transactionAmounts>
            <postTransactionAmounts>
                <sharesOwnedFollowingTransaction>
                    <value>196035.0000</value>
                </sharesOwnedFollowingTransaction>
            </postTransactionAmounts>
            <ownershipNature>
                <directOrIndirectOwnership>
                    <value>D</value>
                </directOrIndirectOwnership>
            </ownershipNature>
        </nonDerivativeTransaction>
        <nonDerivativeTransaction>
            <securityTitle>
                <value>Common Stock</value>
            </securityTitle>
            <transactionDate>
                <value>2016-05-09</value>
            </transactionDate>
            <transactionCoding>
                <transactionFormType>4</transactionFormType>
                <transactionCode>S</transactionCode>
                <equitySwapInvolved>0</equitySwapInvolved>
            </transactionCoding>
            <transactionAmounts>
                <transactionShares>
                    <value>1100.0000</value>
                </transactionShares>
                <transactionPricePerShare>
                    <value>33.7600</value>
                </transactionPricePerShare>
                <transactionAcquiredDisposedCode>
                    <value>D</value>
                </transactionAcquiredDisposedCode>
            </transactionAmounts>
            <postTransactionAmounts>
                <sharesOwnedFollowingTransaction>
                    <value>194935.0000</value>
                </sharesOwnedFollowingTransaction>
            </postTransactionAmounts>
            <ownershipNature>
                <directOrIndirectOwnership>
                    <value>D</value>
                </directOrIndirectOwnership>
            </ownershipNature>
        </nonDerivativeTransaction>
        <nonDerivativeTransaction>
            <securityTitle>
                <value>Common Stock</value>
            </securityTitle>
            <transactionDate>
                <value>2016-05-09</value>
            </transactionDate>
            <transactionCoding>
                <transactionFormType>4</transactionFormType>
                <transactionCode>S</transactionCode>
                <equitySwapInvolved>0</equitySwapInvolved>
            </transactionCoding>
            <transactionAmounts>
                <transactionShares>
                    <value>1600.0000</value>
                </transactionShares>
                <transactionPricePerShare>
                    <value>33.7500</value>
                </transactionPricePerShare>
                <transactionAcquiredDisposedCode>
                    <value>D</value>
                </transactionAcquiredDisposedCode>
            </transactionAmounts>
            <postTransactionAmounts>
                <sharesOwnedFollowingTransaction>
                    <value>193335.0000</value>
                </sharesOwnedFollowingTransaction>
            </postTransactionAmounts>
            <ownershipNature>
                <directOrIndirectOwnership>
                    <value>D</value>
                </directOrIndirectOwnership>
            </ownershipNature>
        </nonDerivativeTransaction>
        <nonDerivativeTransaction>
            <securityTitle>
                <value>Common Stock</value>
            </securityTitle>
            <transactionDate>
                <value>2016-05-09</value>
            </transactionDate>
            <transactionCoding>
                <transactionFormType>4</transactionFormType>
                <transactionCode>S</transactionCode>
                <equitySwapInvolved>0</equitySwapInvolved>
            </transactionCoding>
            <transactionAmounts>
                <transactionShares>
                    <value>4600.0000</value>
                </transactionShares>
                <transactionPricePerShare>
                    <value>33.7300</value>
                </transactionPricePerShare>
                <transactionAcquiredDisposedCode>
                    <value>D</value>
                </transactionAcquiredDisposedCode>
            </transactionAmounts>
            <postTransactionAmounts>
                <sharesOwnedFollowingTransaction>
                    <value>188735.0000</value>
                </sharesOwnedFollowingTransaction>
            </postTransactionAmounts>
            <ownershipNature>
                <directOrIndirectOwnership>
                    <value>D</value>
                </directOrIndirectOwnership>
            </ownershipNature>
        </nonDerivativeTransaction>
        <nonDerivativeTransaction>
            <securityTitle>
                <value>Common Stock</value>
            </securityTitle>
            <transactionDate>
                <value>2016-05-09</value>
            </transactionDate>
            <transactionCoding>
                <transactionFormType>4</transactionFormType>
                <transactionCode>S</transactionCode>
                <equitySwapInvolved>0</equitySwapInvolved>
            </transactionCoding>
            <transactionAmounts>
                <transactionShares>
                    <value>8400.0000</value>
                </transactionShares>
                <transactionPricePerShare>
                    <value>33.7200</value>
                </transactionPricePerShare>
                <transactionAcquiredDisposedCode>
                    <value>D</value>
                </transactionAcquiredDisposedCode>
            </transactionAmounts>
            <postTransactionAmounts>
                <sharesOwnedFollowingTransaction>
                    <value>180335.0000</value>
                </sharesOwnedFollowingTransaction>
            </postTransactionAmounts>
            <ownershipNature>
                <directOrIndirectOwnership>
                    <value>D</value>
                </directOrIndirectOwnership>
            </ownershipNature>
        </nonDerivativeTransaction>
        <nonDerivativeTransaction>
            <securityTitle>
                <value>Common Stock</value>
            </securityTitle>
            <transactionDate>
                <value>2016-05-09</value>
            </transactionDate>
            <transactionCoding>
                <transactionFormType>4</transactionFormType>
                <transactionCode>S</transactionCode>
                <equitySwapInvolved>0</equitySwapInvolved>
            </transactionCoding>
            <transactionAmounts>
                <transactionShares>
                    <value>8900.0000</value>
                </transactionShares>
                <transactionPricePerShare>
                    <value>33.7100</value>
                </transactionPricePerShare>
                <transactionAcquiredDisposedCode>
                    <value>D</value>
                </transactionAcquiredDisposedCode>
            </transactionAmounts>
            <postTransactionAmounts>
                <sharesOwnedFollowingTransaction>
                    <value>171435.0000</value>
                </sharesOwnedFollowingTransaction>
            </postTransactionAmounts>
            <ownershipNature>
                <directOrIndirectOwnership>
                    <value>D</value>
                </directOrIndirectOwnership>
            </ownershipNature>
        </nonDerivativeTransaction>
        <nonDerivativeTransaction>
            <securityTitle>
                <value>Common Stock</value>
            </securityTitle>
            <transactionDate>
                <value>2016-05-09</value>
            </transactionDate>
            <transactionCoding>
                <transactionFormType>4</transactionFormType>
                <transactionCode>S</transactionCode>
                <equitySwapInvolved>0</equitySwapInvolved>
            </transactionCoding>
            <transactionAmounts>
                <transactionShares>
                    <value>39584.0000</value>
                </transactionShares>
                <transactionPricePerShare>
                    <value>33.7000</value>
                </transactionPricePerShare>
                <transactionAcquiredDisposedCode>
                    <value>D</value>
                </transactionAcquiredDisposedCode>
            </transactionAmounts>
            <postTransactionAmounts>
                <sharesOwnedFollowingTransaction>
                    <value>131851.0000</value>
                </sharesOwnedFollowingTransaction>
            </postTransactionAmounts>
            <ownershipNature>
                <directOrIndirectOwnership>
                    <value>D</value>
                </directOrIndirectOwnership>
            </ownershipNature>
        </nonDerivativeTransaction>
        <nonDerivativeHolding>
            <securityTitle>
                <value>Common Stock</value>
            </securityTitle>
            <postTransactionAmounts>
                <sharesOwnedFollowingTransaction>
                    <value>600.0000</value>
                </sharesOwnedFollowingTransaction>
            </postTransactionAmounts>
            <ownershipNature>
                <directOrIndirectOwnership>
                    <value>I</value>
                </directOrIndirectOwnership>
                <natureOfOwnership>
                    <value>By Rule 16b-3 Plan</value>
                </natureOfOwnership>
            </ownershipNature>
        </nonDerivativeHolding>
    </nonDerivativeTable>

    <derivativeTable>
        <derivativeTransaction>
            <securityTitle>
                <value>Employee Stock Option (right to buy)</value>
            </securityTitle>
            <conversionOrExercisePrice>
                <value>22.2800</value>
            </conversionOrExercisePrice>
            <transactionDate>
                <value>2016-05-09</value>
            </transactionDate>
            <transactionCoding>
                <transactionFormType>4</transactionFormType>
                <transactionCode>M</transactionCode>
                <equitySwapInvolved>0</equitySwapInvolved>
            </transactionCoding>
            <transactionAmounts>
                <transactionShares>
                    <value>23884.0000</value>
                </transactionShares>
                <transactionPricePerShare>
                    <value>0.0000</value>
                </transactionPricePerShare>
                <transactionAcquiredDisposedCode>
                    <value>D</value>
                </transactionAcquiredDisposedCode>
            </transactionAmounts>
            <exerciseDate>
                <value>2011-02-28</value>
            </exerciseDate>
            <expirationDate>
                <value>2018-02-28</value>
            </expirationDate>
            <underlyingSecurity>
                <underlyingSecurityTitle>
                    <value>Common Stock</value>
                </underlyingSecurityTitle>
                <underlyingSecurityShares>
                    <value>23884.0000</value>
                </underlyingSecurityShares>
            </underlyingSecurity>
            <postTransactionAmounts>
                <sharesOwnedFollowingTransaction>
                    <value>0.0000</value>
                </sharesOwnedFollowingTransaction>
            </postTransactionAmounts>
            <ownershipNature>
                <directOrIndirectOwnership>
                    <value>D</value>
                </directOrIndirectOwnership>
            </ownershipNature>
        </derivativeTransaction>
    </derivativeTable>

    <footnotes></footnotes>

    <ownerSignature>
        <signatureName>Susan E. Grant, by power of atty., for Sally Susman</signatureName>
        <signatureDate>2016-05-11</signatureDate>
    </ownerSignature>
</ownershipDocument>